lpd/__init__.py
lpd/input_output_label.py
lpd/predictor.py
lpd/trainer.py
lpd/trainer_stats.py
lpd/callbacks/__init__.py
lpd/callbacks/callback_base.py
lpd/callbacks/callback_context.py
lpd/callbacks/callback_monitor.py
lpd/callbacks/callback_monitor_result.py
lpd/callbacks/collect_outputs.py
lpd/callbacks/early_stopping.py
lpd/callbacks/loss_optimizer_handler.py
lpd/callbacks/loss_optimizer_handler_accumulate_batchs.py
lpd/callbacks/loss_optimizer_handler_accumulate_samples.py
lpd/callbacks/loss_optimizer_handler_base.py
lpd/callbacks/model_checkpoint.py
lpd/callbacks/scheduler_step.py
lpd/callbacks/stats_print.py
lpd/callbacks/tensorboard.py
lpd/callbacks/tensorboard_image.py
lpd/enums/__init__.py
lpd/enums/confusion_matrix_based_metric.py
lpd/enums/metric_method.py
lpd/enums/monitor_mode.py
lpd/enums/monitor_type.py
lpd/enums/phase.py
lpd/enums/state.py
lpd/enums/stats_type.py
lpd/extensions/__init__.py
lpd/extensions/custom_layers.py
lpd/extensions/custom_schedulers.py
lpd/metrics/__init__.py
lpd/metrics/binary_accuracy.py
lpd/metrics/binary_accuracy_with_logits.py
lpd/metrics/categorical_accuracy.py
lpd/metrics/categorical_accuracy_with_logits.py
lpd/metrics/confusion_matrix.py
lpd/metrics/metric_base.py
lpd/metrics/mock_metric.py
lpd/metrics/top_k_categorical_accuracy.py
lpd/metrics/tp_tn_fp_fn.py
lpd/utils/__init__.py
lpd/utils/file_utils.py
lpd/utils/general_utils.py
lpd/utils/threshold_checker.py
lpd/utils/torch_utils.py
lpd-0.4.12.dist-info/LICENSE.txt
lpd-0.4.12.dist-info/METADATA
lpd-0.4.12.dist-info/WHEEL
lpd-0.4.12.dist-info/top_level.txt
lpd-0.4.12.dist-info/RECORD
