Metadata-Version: 2.1
Name: lpd
Version: 0.4.12
Summary: A Fast, Flexible Trainer with Callbacks and Extensions for PyTorch
Home-page: https://github.com/roysadaka/lpd
Author: Roy Sadaka
Maintainer: lpd developers
Maintainer-email: torch.lpd@gmail.com
License: MIT Licences
Keywords: pytorch,trainer,callback,callbacks,earlystopping,tensorboard,modelcheckpoint,checkpoint,layers,dense,metrics,predictor,binary accuracy,extensions,track,monitor,machine,deep learning,neural,networks,AI,keras decay,confusion matrix
Classifier: Development Status :: 4 - Beta
Classifier: Intended Audience :: Developers
Classifier: Intended Audience :: Education
Classifier: License :: OSI Approved :: MIT License
Classifier: Operating System :: OS Independent
Classifier: Programming Language :: Python :: 3
Classifier: Programming Language :: Python :: 3.9
Classifier: Topic :: Scientific/Engineering :: Artificial Intelligence
Classifier: Topic :: Utilities
Requires-Python: >=3.9
License-File: LICENSE.txt
Requires-Dist: tensorboard
Requires-Dist: numpy
Requires-Dist: torch
Requires-Dist: torchvision
Requires-Dist: tqdm
